reopenwebnet/__init__.py
reopenwebnet/client_factory.py
reopenwebnet/commandclient.py
reopenwebnet/config.py
reopenwebnet/eventclient.py
reopenwebnet/gatewayproxy.py
reopenwebnet/messages.py
reopenwebnet/password.py
reopenwebnet/protocol.py
reopenwebnet-1.6.0.dist-info/AUTHORS.rst
reopenwebnet-1.6.0.dist-info/LICENSE.txt
reopenwebnet-1.6.0.dist-info/METADATA
reopenwebnet-1.6.0.dist-info/WHEEL
reopenwebnet-1.6.0.dist-info/top_level.txt
reopenwebnet-1.6.0.dist-info/RECORD
