Metadata-Version: 2.1
Name: reopenwebnet
Version: 1.6.0
Summary: An OpenWebNet client
Home-page: https://github.com/karel1980/reopenwebnet
Author: karel1980
Author-email: karel@vervaeke.info
License: mit
Platform: any
Classifier: Development Status :: 4 - Beta
Classifier: Programming Language :: Python
Requires-Python: >=3.7
Requires-Dist: pyyaml (>=5.3)
Requires-Dist: paho-mqtt (>=1.5)
Provides-Extra: testing
Requires-Dist: pytest ; extra == 'testing'
Requires-Dist: pytest-cov ; extra == 'testing'
